dataconf_dbx/__init__.py
dataconf_dbx/exceptions.py
dataconf_dbx/main.py
dataconf_dbx/mocks/dbutils.py
dataconf_dbx/utils.py
dataconf_dbx-0.0.2.dist-info/LICENSE
dataconf_dbx-0.0.2.dist-info/METADATA
dataconf_dbx-0.0.2.dist-info/WHEEL
dataconf_dbx-0.0.2.dist-info/RECORD
