Metadata-Version: 2.1
Name: dataconf_dbx
Version: 0.0.2
Summary: Dataconf adapter for reading configurations from Databricks dbutils.
Home-page: https://github.com/Shlomigreen/dataconf-dbx
Author: Shlomi Green
Author-email: fshlomi.a7@gmail.com
Requires-Python: >=3.8,<4.0
Classifier: Programming Language :: Python :: 3
Classifier: Programming Language :: Python :: 3.8
Classifier: Programming Language :: Python :: 3.9
Classifier: Programming Language :: Python :: 3.10
Classifier: Programming Language :: Python :: 3.11
Classifier: Programming Language :: Python :: 3.12
Requires-Dist: dataconf (>=3.1.0,<4.0.0)
Project-URL: Documentation, https://Shlomigreen.github.io/dataconf-dbx/
Project-URL: Repository, https://github.com/Shlomigreen/dataconf-dbx
